mlu_tools/__init__.py
mlu_tools/classify.py
mlu_tools/consts.py
mlu_tools/custom.py
mlu_tools/data_structure.py
mlu_tools/decorators.py
mlu_tools/mediapipe_utils.py
mlu_tools/utils.py
mlu_tools/validation.py
mlu_tools/keras_utils/__init__.py
mlu_tools/keras_utils/custom_callbacks.py
mlu_tools/keras_utils/model_architectures.py
mlu_tools/keras_utils/preprocessing/__init__.py
mlu_tools/keras_utils/preprocessing/image.py
mlu_tools/plotting/__init__.py
mlu_tools/plotting/grid_plot.py
mlu_tools/plotting/plotting.py
mlu_tools/processing/__init__.py
mlu_tools/processing/image.py
mlu_tools/processing/video.py
mlu_tools-0.0.39.dist-info/METADATA
mlu_tools-0.0.39.dist-info/WHEEL
mlu_tools-0.0.39.dist-info/top_level.txt
mlu_tools-0.0.39.dist-info/RECORD
